compiler_lab_manual/__init__.py
compiler_lab_manual/post_install.py
compiler_lab_manual/lab_manuals/arithmetic.txt
compiler_lab_manual/lab_manuals/calculator.txt
compiler_lab_manual/lab_manuals/comments.txt
compiler_lab_manual/lab_manuals/consonants.txt
compiler_lab_manual/lab_manuals/ifvalid.txt
compiler_lab_manual/lab_manuals/tac-al.txt
compiler_lab_manual/lab_manuals/token program.txt
compiler_lab_manual/lab_manuals/validvariable.txt
compiler_lab_manual-1.1.4.dist-info/LICENSE.txt
compiler_lab_manual-1.1.4.dist-info/METADATA
compiler_lab_manual-1.1.4.dist-info/WHEEL
compiler_lab_manual-1.1.4.dist-info/top_level.txt
compiler_lab_manual-1.1.4.dist-info/RECORD
