Metadata-Version: 2.1
Name: compiler-lab-manual
Version: 1.1.4
Summary: A package for Compiler Lab Manual exercises
Home-page: https://github.com/trackers-new/compiler-lab-manual
Author: Problem Solver
Author-email: treecse@gmail.com
License: MIT
Classifier: Programming Language :: Python :: 3
Classifier: License :: OSI Approved :: MIT License
Classifier: Operating System :: OS Independent
Requires-Python: >=3.6
License-File: LICENSE.txt
